README.rst
setup.py
deadlineutils/__init__.py
deadlineutils/deadlineconnection.py
deadlineutils.egg-info/PKG-INFO
deadlineutils.egg-info/SOURCES.txt
deadlineutils.egg-info/dependency_links.txt
deadlineutils.egg-info/top_level.txt
deadlineutils/packages/__init__.py
deadlineutils/packages/Deadline/Balancer.py
deadlineutils/packages/Deadline/ConnectionProperty.py
deadlineutils/packages/Deadline/DeadlineConnect.py
deadlineutils/packages/Deadline/DeadlineSend.py
deadlineutils/packages/Deadline/Groups.py
deadlineutils/packages/Deadline/JobReports.py
deadlineutils/packages/Deadline/Jobs.py
deadlineutils/packages/Deadline/Limits.py
deadlineutils/packages/Deadline/MappedPaths.py
deadlineutils/packages/Deadline/MaximumPriority.py
deadlineutils/packages/Deadline/Plugins.py
deadlineutils/packages/Deadline/Pools.py
deadlineutils/packages/Deadline/Pulse.py
deadlineutils/packages/Deadline/Repository.py
deadlineutils/packages/Deadline/Slaves.py
deadlineutils/packages/Deadline/SlavesRenderingJob.py
deadlineutils/packages/Deadline/TaskReports.py
deadlineutils/packages/Deadline/Tasks.py
deadlineutils/packages/Deadline/Users.py
deadlineutils/packages/Deadline/__init__.py