Metadata-Version: 1.1
Name: deadlineutils
Version: 0.1.0
Summary: Deadline utilities
Home-page: http://github.com/danbradham/deadlineutils.git
Author: Dan Bradham
Author-email: danielbradham@gmail.com
License: None
Platform: UNKNOWN
Classifier: Development Status :: 3 - Alpha
Classifier: Intended Audience :: Developers
Classifier: Natural Language :: English
Classifier: Operating System :: OS Independent
Classifier: Programming Language :: Python
Classifier: Programming Language :: Python :: 2
